{
  "resourceType": "ValueSet",
  "id": "2.16.840.1.113883.3.6037.1001.23.99.80",
  "meta": {
    "versionId": "1",
    "lastUpdated": "2020-09-21T06:15:58.000+00:00",
    "source": "#U6vqWVOE8qzxxs5q"
  },
  "url": "http://localhost:8082/interop/fhir/ValueSet/2.16.840.1.113883.3.6037.1001.23.99.80",
  "identifier": [
    {
      "system": "urn:ietf:rfc:3986",
      "value": "2.16.840.1.113883.3.6037.1001.23.99.80"
    }
  ],
  "version": "Latest",
  "name": "Panniculectomy",
  "title": "Panniculectomy",
  "status": "active",
  "publisher": "Mettles",
  "compose": {
    "include": [
      {
        "system": "https://www.aapc.com/resources/medical-coding/cpt.aspx",
        "version": "2020-07",
        "concept": [
          {
            "code": "15830",
            "display": "Excision, excessive skin and subcutaneous tissue (includes lipectomy); abdomen, infraumbilical panniculectomy"
          },
          {
            "code": "15847",
            "display": "Under Other Repair (Closure) Procedures on the Integumentary System"
          },
          {
            "code": "15877",
            "display": "Suction assisted lipectomy; trunk"
          }
        ]
      }
    ]
  }
}